barg/__init__.py
barg/__main__.py
barg/barg_codegen.py
barg/barg_codegen_builtins.py
barg/barg_core.py
barg/barg_exec_builtins.py
barnii77_barg-0.2.3.dist-info/LICENSE.txt
barnii77_barg-0.2.3.dist-info/METADATA
barnii77_barg-0.2.3.dist-info/WHEEL
barnii77_barg-0.2.3.dist-info/top_level.txt
barnii77_barg-0.2.3.dist-info/RECORD
