Metadata-Version: 2.1
Name: barnii77-barg
Version: 0.2.3
Summary: Barni's tiny parser generator for parsing strings/code
Classifier: Programming Language :: Python :: 3
Classifier: License :: OSI Approved :: MIT License
Classifier: Operating System :: OS Independent
Requires-Python: >=3.8
License-File: LICENSE.txt
Requires-Dist: regex
